[
    {
        "nickname": "Guidoti",
        "name": "Guido Enrique",
        "description": "Tambien llamado 'Eden Hazard criado a puchos'. En su mejor dia te mete +3 goles, te la deja en el pie y no lo agarras, pero en un dia normal es el mas perro de la cancha. Vos tantealo, y tomas la decision de pasarsela o no a este flor de amargo.",
        "age": 23,
        "rank": 3,
        "position": "volante",
        "totalGoals": 0,
        "gamesPlayed": 0,
        "gamesWon": 0,
        "gamesLost": 0
    },
    {
        "nickname": "Marcos",
        "name": "Marcos Fitzsimons",
        "description": "Jugador de elite, con cosas de 'Kevin de Bruyne' en sus dias. Cuando esta en su PRIME, este pibe realmente cuida la caprichosa y genera situaciones de goles, pero de no ser asi, te putea.",
        "age": 24,
        "rank": 5,
        "position": "volante",
        "totalGoals": 0,
        "gamesPlayed": 0,
        "gamesWon": 0,
        "gamesLost": 0
    },
    {
        "nickname": "Marto",
        "name": "Martin Chapman",
        "description": "Nuestro 'Virgil Van Dijk', de mas de 2 metros (donde 1.5 metros corresponden a las piernas). No se entiende la agilidad de este hijo de puta, imposible encararlo. Si juega en contra olvidate del juego aereo",
        "age": 23,
        "rank": 4,
        "position": "defensor",
        "totalGoals": 0,
        "gamesPlayed": 0,
        "gamesWon": 0,
        "gamesLost": 0
    },
    {
        "nickname": "Nacho",
        "name": "Ignacio Rivarola",
        "description": "Tremenda gallina, con destellos de 'Dani Alves' en su mejor dia, a veces le pega y no entendes el golazo que mete. Cumplidor... pero en un dia normal? le tiras un pase y no la sabe parar, gallina amarga",
        "age": 23,
        "rank": 3,
        "position": "defensor",
        "totalGoals": 0,
        "gamesPlayed": 0,
        "gamesWon": 0,
        "gamesLost": 0
    },
    {
        "nickname": "Leo",
        "name": "Leonardo Usar",
        "description": "Boca por sobre todas las cosas. Sabe ser 'Luis Suarez' en un buen dia, +4 goles por partido, le apunta al corner y te mete un gol (ni el sabe como los hace). Aprovechalo un dia que no vaya a donar sangre, porque sino, es lo mismo poner un cono en la cancha. Con razon empezaste a jugar al paddle",
        "age": 30,
        "rank": 4,
        "position": "delantero",
        "totalGoals": 0,
        "gamesPlayed": 0,
        "gamesWon": 0,
        "gamesLost": 0
    },
    {
        "nickname": "Goyo",
        "name": "Gregorio Zanzottera",
        "description": "Soldado complicado de pasar, de los mas regulares del equipo. Conocido tambien como 'Oscar Ruggeri', pasa la pelota o pasas vos... y bueno, algunos dias pasa hasta el viento",
        "age": 23,
        "rank": 3,
        "position": "defensor",
        "totalGoals": 0,
        "gamesPlayed": 0,
        "gamesWon": 0,
        "gamesLost": 0
    },
    {
        "nickname": "Oliveti",
        "name": "Nicolas Oliva",
        "description": "JOGO BONITO, Futbol Playa, Brasilero de nacimiento. Iluminado por 'O Rei'. Magia y distribucion, nuestro 'Ronaldinho'. Tambien con lo malo, falta a entrenar, llega fumado y aveces de gira. 'Ricky Centurion' le diria yo",
        "age": 23,
        "rank": 5,
        "position": "volante",
        "totalGoals": 0,
        "gamesPlayed": 0,
        "gamesWon": 0,
        "gamesLost": 0
    },
    {
        "nickname": "Flaco",
        "name": "Augusto Depierro",
        "description": "en honor al 'Flaco Schiavi'. Otro mas que te caga a patadas y no te deja pasar ni loco, es como chocarse una pared (algunos dias, otros dias rezas porque te toque en contra)",
        "age": 23,
        "rank": 2,
        "position": "defensor",
        "totalGoals": 0,
        "gamesPlayed": 0,
        "gamesWon": 0,
        "gamesLost": 0
    },
    {
        "nickname": "Gonza",
        "name": "Gonzalo Fitzsimons",
        "description": "El jugador mas volatil del plantel. Ponelo donde quieras que te cumple, con la sangre Fitzsimons que garantiza calidad. 'Marcelo', lo bueno que si esta en modo perro se calienta con el solo nomas.",
        "age": 30,
        "rank": 4,
        "position": "defensor",
        "totalGoals": 0,
        "gamesPlayed": 0,
        "gamesWon": 0,
        "gamesLost": 0
    },
    {
        "nickname": "Kapanga",
        "name": "Genaro Moretti",
        "description": "De este hay mucho que decir... pero lo limitamos a un 'Gonzalo Higuain'. Nada mas. Se suele conformar con tirar caños antes que ganar o hacer goles. Es una bala que sale bien o te puede dar ganas de no jugar mas al futbol.",
        "age": 23,
        "rank": 3,
        "position": "delantero",
        "totalGoals": 0,
        "gamesPlayed": 0,
        "gamesWon": 0,
        "gamesLost": 0
    },
    {
        "nickname": "Manucho",
        "name": "Manuel Echenique",
        "description": "Se siguen haciendo estudios para determinar si es zurdo o derecho (hoy en dia se cree que es zurdo), Un 'Jordi Alba' pasado un poco de peso que en un EXCELENTE dia no falla.",
        "age": 24,
        "rank": 2,
        "position": "defensor",
        "totalGoals": 0,
        "gamesPlayed": 0,
        "gamesWon": 0,
        "gamesLost": 0
    },
    {
        "nickname": "Serra",
        "name": "Facundo Serrano",
        "description": "Y este? sisi, juega al futbol che. Corre como un enfermito, 'Antonio Valencia' en su prime, buen estado. No mas que eso, mucho instagram, poco fulbo.",
        "age": 23,
        "rank": 2,
        "position": "defensor",
        "totalGoals": 0,
        "gamesPlayed": 0,
        "gamesWon": 0,
        "gamesLost": 0
    }
]